Py3Challenges/__init__.py
Py3Challenges/challenge.py
Py3Challenges/helper.py
Py3Challenges/saves/__init__.py
Py3Challenges/saves/challenges/__init__.py
Py3Challenges/saves/challenges/c0_print.py
Py3Challenges/saves/challenges/c1_addition.py
Py3Challenges/saves/challenges/c2_subtraction.py
Py3Challenges/saves/challenges/c3_multiplication.py
Py3Challenges/saves/challenges/c4_division.py
Py3Challenges/saves/challenges/c5_sum.py
Py3Challenges/saves/challenges/c6_min.py
Py3Challenges/saves/challenges/c7_max.py
Py3Challenges-1.1.0.dist-info/LICENSE
Py3Challenges-1.1.0.dist-info/METADATA
Py3Challenges-1.1.0.dist-info/WHEEL
Py3Challenges-1.1.0.dist-info/top_level.txt
Py3Challenges-1.1.0.dist-info/RECORD
