Metadata-Version: 2.1
Name: Py3Challenges
Version: 1.1.0
Summary: A collection of challenges for programming beginners.
Home-page: https://github.com/AlbertUnruh/Py3Challenges
Author: AlbertUnruh
License: MIT
Project-URL: Issue Tracker, https://github.com/AlbertUnruh/Py3Challenges/issues
Project-URL: Source Code, https://github.com/AlbertUnruh/Py3Challenges
Keywords: albert unruh tutorial challenge
Platform: UNKNOWN
Classifier: Intended Audience :: Developers
Classifier: License :: OSI Approved :: MIT License
Classifier: Operating System :: OS Independent
Classifier: Programming Language :: Python :: 3
Classifier: Programming Language :: Python :: 3.9
Classifier: Programming Language :: Python :: 3.10
Classifier: Programming Language :: Python :: 3.11
Classifier: Topic :: Software Development :: Libraries
Classifier: Topic :: Software Development :: Libraries :: Python Modules
Classifier: Typing :: Typed
Requires-Python: >=3.9
License-File: LICENSE
